timezone_tools/__init__.py
timezone_tools/_clock.py
timezone_tools/_converter.py
timezone_tools/_dates.py
timezone_tools/py.typed
timezone_tools-0.1.0.post1.dist-info/licenses/LICENSE
timezone_tools-0.1.0.post1.dist-info/METADATA
timezone_tools-0.1.0.post1.dist-info/WHEEL
timezone_tools-0.1.0.post1.dist-info/top_level.txt
timezone_tools-0.1.0.post1.dist-info/RECORD
