Metadata-Version: 2.4
Name: timezone_tools
Version: 0.1.0.post1
Summary: Tools for working with timezone-aware datetimes.
License-Expression: MIT
Project-URL: Source, https://github.com/kraken-tech/timezone-tools
Project-URL: Changelog, https://github.com/kraken-tech/timezone-tools/blob/main/CHANGELOG.md
Classifier: Operating System :: OS Independent
Classifier: Programming Language :: Python :: 3 :: Only
Classifier: Programming Language :: Python :: 3
Classifier: Programming Language :: Python :: 3.10
Classifier: Programming Language :: Python :: 3.11
Classifier: Programming Language :: Python :: 3.12
Classifier: Programming Language :: Python :: 3.13
Classifier: Typing :: Typed
Requires-Python: >=3.10
License-File: LICENSE
Requires-Dist: python-dateutil
Requires-Dist: typing_extensions
Provides-Extra: dev
Requires-Dist: covdefaults; extra == "dev"
Requires-Dist: coverage; extra == "dev"
Requires-Dist: pre-commit; extra == "dev"
Requires-Dist: pytest; extra == "dev"
Requires-Dist: time-machine; extra == "dev"
Requires-Dist: tox; extra == "dev"
Requires-Dist: tox-uv; extra == "dev"
Requires-Dist: uv; extra == "dev"
Dynamic: license-file
